assets/__init__.py
assets/styles.css
comgra/__init__.py
comgra/objects.py
comgra/recorder.py
comgra/utilities.py
comgra/visualizer.py
scripts/__init__.py
scripts/run.py
scripts/server.py
comgra-0.10.1.dist-info/LICENSE.txt
comgra-0.10.1.dist-info/METADATA
comgra-0.10.1.dist-info/WHEEL
comgra-0.10.1.dist-info/entry_points.txt
comgra-0.10.1.dist-info/top_level.txt
comgra-0.10.1.dist-info/RECORD
