Metadata-Version: 2.1
Name: comgra
Version: 0.10.1
Summary: A package for analyzing computation graphs
Author-email: Florian Dietz <floriandietz44@gmail.com>
Project-URL: Homepage, https://github.com/FlorianDietz/comgra
Project-URL: Bug Tracker, https://github.com/FlorianDietz/comgra/issues
Classifier: Programming Language :: Python :: 3
Classifier: License :: OSI Approved :: MIT License
Classifier: Operating System :: OS Independent
Requires-Python: >=3.7
License-File: LICENSE.txt
Requires-Dist: torch
Requires-Dist: dash
Requires-Dist: dash-svg
Requires-Dist: dash-bootstrap-components >=1.5.0
Requires-Dist: msgpack
Requires-Dist: numpy
Requires-Dist: pandas
